pysis/__init__.py
pysis/cubefile.py
pysis/env.py
pysis/exceptions.py
pysis/isis.py
pysis/isiscommand.py
pysis/isispool.py
pysis/specialpixels.py
pysis/binning/__init__.py
pysis/binning/abstract.py
pysis/binning/bounded.py
pysis/binning/const_width.py
pysis/binning/geometric.py
pysis/util/__init__.py
pysis/util/file_manipulation.py
pysis-0.6.0.dist-info/DESCRIPTION.rst
pysis-0.6.0.dist-info/METADATA
pysis-0.6.0.dist-info/RECORD
pysis-0.6.0.dist-info/WHEEL
pysis-0.6.0.dist-info/metadata.json
pysis-0.6.0.dist-info/top_level.txt
