Metadata-Version: 1.1
Name: pysis
Version: 0.6.0
Summary: Toolkit for using USGS Isis in Python.
Home-page: https://github.com/wtolson/pysis
Author: Trevor Olson
Author-email: trevor@heytrevor.com
License: BSD
Keywords: pysis
Platform: UNKNOWN
Classifier: Development Status :: 2 - Pre-Alpha
Classifier: Intended Audience :: Developers
Classifier: License :: OSI Approved :: BSD License
Classifier: Natural Language :: English
Classifier: Programming Language :: Python :: 2
Classifier: Programming Language :: Python :: 2.6
Classifier: Programming Language :: Python :: 2.7
Classifier: Programming Language :: Python :: 3
Classifier: Programming Language :: Python :: 3.3
Classifier: Programming Language :: Python :: 3.4
